tesaurus/__init__.py
tesaurus/perintah.py
tesaurus/tesaurus.py
tesaurus-0.1.3.dist-info/LICENSE
tesaurus-0.1.3.dist-info/METADATA
tesaurus-0.1.3.dist-info/WHEEL
tesaurus-0.1.3.dist-info/entry_points.txt
tesaurus-0.1.3.dist-info/top_level.txt
tesaurus-0.1.3.dist-info/RECORD
