Metadata-Version: 2.1
Name: tesaurus
Version: 0.1.3
Summary: Sebuah modul Python untuk mengambil informasi Tesaurus dari Tesaurus Tematis Kemdikbud
Home-page: https://github.com/noaione/tesaurus-python
Author: noaione
Author-email: noaione0809@gmail.com
License: MIT
Keywords: tesaurus,lema,bahasa,indonesia,scraper,async
Platform: UNKNOWN
Classifier: Development Status :: 5 - Production/Stable
Classifier: Environment :: Console
Classifier: Intended Audience :: Developers
Classifier: Intended Audience :: Education
Classifier: Intended Audience :: End Users/Desktop
Classifier: License :: OSI Approved :: MIT License
Classifier: Natural Language :: Indonesian
Classifier: Operating System :: OS Independent
Classifier: Programming Language :: Python :: 3
Classifier: Programming Language :: Python :: 3.6
Classifier: Programming Language :: Python :: 3.7
Classifier: Programming Language :: Python :: 3.8
Classifier: Programming Language :: Python :: 3.9
Classifier: Programming Language :: Python :: 3 :: Only
Classifier: Topic :: Software Development :: Libraries :: Python Modules
Classifier: Topic :: Text Processing :: Linguistic
Requires-Python: >=3.6
License-File: LICENSE
Requires-Dist: beautifulsoup4
Requires-Dist: requests
Requires-Dist: aiohttp
